<resources xmlns:xsi="http://www.w3.org/2001/XMLSchema-instance">
	<string key="12_RegentJinJae" gender="Female" rel_version="Quest_MSQ2_Revamp">Jin Jae, caballera regente</string>
	<string key="12_RegentJinJae_title" rel_version="Quest_MSQ2_Revamp">Riscos del Monarca</string>
	<string key="12_RegentJinJae_title1" rel_version="Quest_MSQ2_Revamp">Reina coronada de Riscos del Monarca</string>
	<string key="12_Lochnir" gender="Male" rel_version="Quest_MSQ2_Revamp">Ministro Lochnir</string>
	<string key="12_Lochnir_title" rel_version="Quest_MSQ2_Revamp">Riscos del Monarca</string>
	<string key="12_MB_Grace_title" rel_version="Quest_MSQ2_Revamp">Superviviente del naufragio</string>
	<string key="12_GaetanFortier" gender="Male" rel_version="Quest_MSQ2_Revamp">Gaetan Fortier</string>
	<string key="12_GaetanFortier_title" rel_version="Quest_MSQ2_Revamp">Capitán de la guardia</string>
	<string key="12_AllyaMusa" gender="Female" rel_version="Quest_MSQ2_Revamp">Allya Musa</string>
	<string key="12_AllyaMusa_title" rel_version="Quest_MSQ2_Revamp">Capataz de la mina</string>
	<string key="12_EliasDerit" gender="Male" rel_version="Quest_MSQ2_Revamp">Elías Derit</string>
	<string key="12_EliasDerit_title" rel_version="Quest_MSQ2_Revamp">Minero</string>
	<string key="12_AsheDubois" gender="Female" rel_version="Quest_MSQ2_Revamp">Ashe Dubois</string>
	<string key="12_AsheDubois_title" rel_version="Quest_MSQ2_Revamp">Escudera de Riscos del Monarca</string>
	<string key="12_SerPayneBennett" gender="Male" rel_version="Quest_MSQ2_Revamp">Sir Payne Bennett</string>
	<string key="12_SerPayneBennett_title" rel_version="Quest_MSQ2_Revamp">Caballero de Riscos del Monarca</string>
	<string key="12_PercillaWallen" gender="Female" rel_version="Quest_MSQ2_Revamp">Percilla Wallen</string>
	<string key="12_PercillaWallen_title" rel_version="Quest_MSQ2_Revamp">Granjera</string>
	<string key="12_PercillaWallen_title1" rel_version="Quest_MSQ2_Revamp">Caballera de Riscos del Monarca</string>
	<string key="12_OldeGeiser" gender="Male" rel_version="Quest_MSQ2_Revamp">Olde Geiser</string>
	<string key="12_OldeGeiser_title" rel_version="Quest_MSQ2_Revamp">Creador de memoriales</string>
	<string key="12_EddaYonkers" gender="Female" rel_version="Quest_MSQ2_Revamp">Edda Yonkers</string>
	<string key="12_EddaYonkers_title" rel_version="Quest_MSQ2_Revamp">Costurera</string>
	<string key="12_FionaMurphy" gender="Female" rel_version="Quest_MSQ2_Revamp">Fiona Murphy</string>
	<string key="12_FionaMurphy_title" rel_version="Quest_MSQ2_Revamp">Trovadora de Riscos del Monarca</string>
	<string key="12_HugoMolina" gender="Male" rel_version="Quest_MSQ2_Revamp">Hugo Molina</string>
	<string key="12_HugoMolina_title" rel_version="Quest_MSQ2_Revamp">Caballero de Riscos del Monarca</string>
	<string key="12_JeongNabi" gender="Female" rel_version="Quest_MSQ2_Revamp">Jeong Nabi</string>
	<string key="12_JeongNabi_title" rel_version="Quest_MSQ2_Revamp">Ma-Ma</string>
	<string key="12_JeongIseul" gender="Female" rel_version="Quest_MSQ2_Revamp">Jeong Iseul</string>
	<string key="12_JeongIseul_title" rel_version="Quest_MSQ2_Revamp">Ma-Ma</string>
	<string key="12_HamzaKillic" gender="Male" rel_version="Quest_MSQ2_Revamp">Hamza Killic</string>
	<string key="12_HamzaKillic_title" rel_version="Quest_MSQ2_Revamp">Mecánico dental</string>
	<string key="12_OliviaBarovier" gender="Female" rel_version="Quest_MSQ2_Revamp">Olivia Barovier</string>
	<string key="12_OliviaBarovier_title" rel_version="Quest_MSQ2_Revamp">Vidriera</string>
	<string key="12_CemalQadir" gender="Male" rel_version="Quest_MSQ2_Revamp">Cemal Qadir</string>
	<string key="12_CemalQadir_title" rel_version="Quest_MSQ2_Revamp">Maestro constructor de Riscos del Monarca</string>
	<string key="12_DayoMusa" gender="Male" rel_version="Quest_MSQ2_Revamp">Dayo Musa</string>
	<string key="12_DayoMusa_title" rel_version="Quest_MSQ2_Revamp">Clérigo</string>
	<string key="12_ShaeGarcia" gender="Female" rel_version="Quest_MSQ2_Revamp">Shae García</string>
	<string key="12_ShaeGarcia_title" rel_version="Quest_MSQ2_Revamp">Escriba de Riscos del Monarca</string>
	<string key="12_DonQuixolay" gender="Male" rel_version="Quest_MSQ2_Revamp">Diego López</string>
	<string key="12_DonQuixolay_title" rel_version="Quest_MSQ2_Revamp">Caballero de Riscos del Monarca</string>
	<string key="12_GeertieLother" gender="Female" rel_version="Quest_MSQ2_Revamp">Geertie Lother</string>
	<string key="12_GeertieLother_title" rel_version="Quest_MSQ2_Revamp">Tabernera</string>
	<string key="12_YoungeGeiser" gender="Male" rel_version="Quest_MSQ2_Revamp">Younge Geiser</string>
	<string key="12_YoungeGeiser_title" rel_version="Quest_MSQ2_Revamp">Sabio de Riscos del Monarca</string>
	<string key="12_ShazaanCortis" gender="Male" rel_version="Quest_MSQ2_Revamp">Shazaan Cortis</string>
	<string key="12_ShazaanCortis_title" rel_version="Quest_MSQ2_Revamp">Minero</string>
	<string key="12_TomiraDudek" gender="Female" rel_version="Quest_MSQ2_Revamp">Tomira Dudek</string>
	<string key="12_TomiraDudek_title" rel_version="Quest_MSQ2_Revamp">Minera</string>
	<string key="12_ChanduIyer" gender="Male" rel_version="Quest_MSQ2_Revamp">Chandu Iyer</string>
	<string key="12_ChanduIyer_title" rel_version="Quest_MSQ2_Revamp">Minero</string>
	<string key="12_KnightsDecree" gender="Object" rel_version="Quest_MSQ2_Revamp">Pergamino conservado</string>
	<string key="12_KnightsDecree_InteractOverride" gender="Object" rel_version="Quest_MSQ2_Revamp">Leer</string>
	<string key="12_ClericLetter" gender="Object" rel_version="Quest_MSQ2_Revamp">Reflexiones garabateadas</string>
	<string key="12_ClericLetter_InteractOverride" gender="Object" rel_version="Quest_MSQ2_Revamp">Leer</string>
	<string key="12_AdjudicatorOwgan" gender="Female" rel_version="Quest_MSQ2_Revamp">Mora Owgan</string>
	<string key="12_AdjudicatorOwgan_title" rel_version="Quest_MSQ2_Revamp">Jueza de Riscos del Monarca</string>
	<string key="12_AlchemistTuit" gender="Male" rel_version="Quest_MSQ2_Revamp">Gyles Tuit</string>
	<string key="12_AlchemistTuit_title" rel_version="Quest_MSQ2_Revamp">Alquimista de Riscos del Monarca</string>
	<string key="12_CommanderPurcell" gender="Male" rel_version="Quest_MSQ2_Revamp">Rodger Purcell</string>
	<string key="12_CommanderPurcell_title" rel_version="Quest_MSQ2_Revamp">Comandante de Riscos del Monarca</string>
	<string key="12_InnkeepBiton" gender="Male" rel_version="Quest_MSQ2_Revamp">Demetrius Biton</string>
	<string key="12_InnkeepBiton_title" rel_version="Quest_MSQ2_Revamp">Posadero de Riscos del Monarca</string>
</resources>

