<resources xmlns:xsi="http://www.w3.org/2001/XMLSchema-instance">
	<string key="ui_calendar_event_button_ok">OK</string>
	<string key="ui_calendar_event_button_next">Próximo</string>
	<string key="ui_calendar_event_button_back">Voltar</string>
	<string key="ui_calendar_event_button_go">Vamos nessa!</string>
	<string key="ui_calendar_event_button_view_details">Ver Detalhes</string>
	<string key="ui_rewardtype_event_progress">&lt;img src="{icon}" xPadding="0" scale="1.8" yOffset="5"&gt;&lt;/img&gt; &lt;font color="#ffffff" &gt; {amount} &lt;/font&gt; &lt;font face="lyshineui/fonts/Nimbus_Medium.font"&gt;{displayName}&lt;/font&gt;</string>
	<string key="ui_event_progress_name">Reputação no Evento</string>
	<string key="ui_event">Evento</string>
	<string key="ui_event_rules">Destaques do Evento</string>
	<string key="ui_calendar_event_button_about" rel_version="PvP_Rewards_Track">&lt;img src="lyshineui/images/icons/misc/icon_question_orange" xPadding="0" scale="1.5" yOffset="1"&gt;&lt;/img&gt; Sobre a Trilha de Recompensas PvP</string>
	<string key="ui_pvp_rewards_panel1_title" rel_version="PvP_Rewards_Track">NOVA TRILHA DE RECOMPENSAS PVP ADICIONADA</string>
	<string key="ui_pvp_rewards_panel1_subtitle" rel_version="PvP_Rewards_Track">A Trilha de Recompensas PvP contém recompensas específicas de PvP por realizar atividades PvP no jogo. A trilha pode ser concluída e executada novamente para obter uma seleção diferente de recompensas, com recompensas mais prestigiosas disponíveis à medida que mais trilhas são concluídas.</string>
	<string key="ui_pvp_rewards_panel1_bullet1_title" rel_version="PvP_Rewards_Track">EXP PVP</string>
	<string key="ui_pvp_rewards_panel1_bullet1_text" rel_version="PvP_Rewards_Track">Faça progresso em sua trilha participando de Missões PvP, Arenas 3v3, Guerras e Investidas do Posto Avançado, capturando fortes, derrotando outros jogadores e recebendo EXP enquanto estiver sinalizado.</string>
	<string key="ui_pvp_rewards_panel1_bullet2_title" rel_version="PvP_Rewards_Track">SAL DE AZOTH</string>
	<string key="ui_pvp_rewards_panel1_bullet2_text" rel_version="PvP_Rewards_Track">Sal de Azoth é uma moeda que permite adquirir recompensas da Trilha PvP. Você pode ganhar Sal de Azoth participando de Guerras, Investidas do Posto Avançado, Arenas 3v3 e Missões PvP, abatendo jogadores no mundo aberto e recebendo EXP enquanto estiver sinalizado.</string>
	<string key="ui_pvp_rewards_panel1_bullet3_title" rel_version="PvP_Rewards_Track">RECOMPENSAS</string>
	<string key="ui_pvp_rewards_panel1_bullet3_text" rel_version="PvP_Rewards_Track">Escolha entre recompensas exclusivas, como armaduras e armas de prestígio, gestos, moedas e consumíveis.</string>
	<string key="ui_event_summer_rank_0" rel_version="Event_Summer_Temp">Menestrel</string>
	<string key="ui_event_summer_rank_1" rel_version="Event_Summer_Temp">Trovador</string>
	<string key="ui_event_summer_rank_2" rel_version="Event_Summer_Temp">Bardo</string>
	<string key="ui_event_summer_rank_3" rel_version="Event_Summer_Temp">Virtuoso</string>
	<string key="ui_event_summer_rank_4" rel_version="Event_Summer_Temp">Maestro</string>
	<string key="ui_event_summer_shop_header" rel_version="Event_Summer_Temp">Loja da Feira de Variedades do Verão</string>
	<string key="ui_event_summer_progress_name" rel_version="Event_Summer_Temp">Reputação no Evento</string>
	<string key="ui_event_summer_panel1_title" rel_version="Event_Summer_Temp">A FEIRA DE VARIEDADES DO VERÃO CHEGOU</string>
	<string key="ui_event_summer_panel1_subtitle" rel_version="Event_Summer_Temp">O evento começa em {startDate}</string>
	<string key="ui_event_summer_panel1_bullet1_title" rel_version="Event_Summer_Temp">ATIVIDADES DE TEMPO LIMITADO</string>
	<string key="ui_event_summer_panel1_bullet1_text" rel_version="Event_Summer_Temp">Vá para a pista de dança, toque música, pegue a isca de Inseto Sentimental e pesque os excepcionalmente deliciosos Esturjões de Aeternum para alimentar o festival; a Feira de Variedades está repleta de atividades para todos!\n\nLembre-se de visitar a estação Peixespetacular para confeccionar lembranças de suas capturas mais orgulhosas!</string>
	<string key="ui_event_summer_panel1_bullet2_title" rel_version="Event_Summer_Temp">RECOMPENSAS DA FEIRA DE VARIEDADES</string>
	<string key="ui_event_summer_panel1_bullet2_text" rel_version="Event_Summer_Temp">As brisas de verão e o Maestro da Feira de Variedades trazem consigo novas armaduras, aparências, gestos e uma variedade de itens de decoração temáticos da colorida e energética Feira de Variedades do Verão!\n\n“Dance e faça compras até estourar o cartão!” - Maestro da Feira de Variedades</string>
	<string key="ui_event_summer_panel1_bullet3_title" rel_version="Event_Summer_Temp">LOCAIS DA FEIRA DE VARIEDADES</string>
	<string key="ui_event_summer_panel1_bullet3_text" rel_version="Event_Summer_Temp">O Maestro da Feira de Variedades montou quatro locais para acomodar a energia borbulhante da Feira de Variedades do Verão! Visite esses locais para conhecer o anfitrião, a equipe e os convidados. Realize suas jornadas de festividades e espalhe alegria por Aeternum!\n(Sequência de jornadas desbloqueada no nível 20)</string>
	<string key="ui_event_summer_panel2_title" rel_version="Event_Summer_Temp">PRODUÇÃO DA FEIRA DE VARIEDADES</string>
	<string key="ui_event_summer_panel2_subtitle" rel_version="Event_Summer_Temp">Celebre a Feira de Variedades do Verão em Aeternum espalhando a energia do festival pelos assentamentos! Conclua Projetos da Vila da Feira de Variedades para aprimorar o Palco da Feira de Variedades de cada assentamento para realçar sua beleza e desbloquear recompensas diárias cada vez mais valiosas!</string>
	<string key="ui_event_summer_panel3_title" rel_version="Event_Summer_Temp">ITENS DA LOJA COM TEMÁTICA DE HEAVY METAL</string>
	<string key="ui_event_summer_panel3_subtitle" rel_version="Event_Summer_Temp">Confira a loja para obter cosméticos e itens de decoração com tema de heavy metal exclusivos!</string>
	<string key="ui_event_summer_lastday_panel1_title" rel_version="Event_Summer_Temp">ÚLTIMO DIA DA FEIRA DE VARIEDADES</string>
	<string key="ui_event_summer_lastday_panel1_subtitle" rel_version="Event_Summer_Temp">A Feira de Variedades deste ano está chegando ao fim. É a última chance de ganhar o máximo possível de Recompensas da Feira de Variedades!\n\n(Os Tokens da Feira de Variedades e outros itens limitados ao evento serão removidos após a conclusão dele.)</string>
	<string key="ui_event_summer_lastday_ending_button" rel_version="Event_Summer_Temp">OK!</string>
	<string key="ui_event_summer_calendar_event_button_about" rel_version="Event_Summer_Temp">&lt;img src="lyshineui/images/icons/misc/icon_question_orange" xPadding="0" scale="1.5" yOffset="1"&gt;&lt;/img&gt; Sobre a Feira de Variedades do Verão</string>
	<string key="ui_event_2xfishing_panel1_title" rel_version="Event_Summer_Temp">FIM DE SEMANA COM O DOBRO DE EXP DE PESCA E MÚSICA!</string>
	<string key="ui_event_2xfishing_panel1_subtitle" rel_version="Event_Summer_Temp">Aproveite o dobro de EXP para Pesca e habilidades mercantes de Instrumentos Musicais todo fim de semana durante o evento da Feira de Variedades do Verão!</string>
	<string key="ui_event_2xfishing_ending_button" rel_version="Event_Summer_Temp">Que maravilha!</string>
	<string key="ui_event_2xfishing_calendar_event_button_about" rel_version="Event_Summer_Temp">&lt;img src="lyshineui/images/icons/misc/icon_question_orange" xPadding="0" scale="1.5" yOffset="1"&gt;&lt;/img&gt; Sobre Pesca e Música para EXP em Dobro</string>
	<string key="ui_event_barnacles_panel1_title" rel_version="Event_Summer_Temp">CRACAS E PÓLVORA PRETA</string>
	<string key="ui_event_barnacles_panel1_subtitle" rel_version="Event_Summer_Temp">Rumores de um tesouro lendário chamado Coração do Oceano, escondido na costa, circularam em Ilhéus do Sabre. Há boatos de que esse tesouro carrega poderes de domínio e controle e pode ameaçar o assentamento de Ilhéus do Sabre e além.</string>
	<string key="ui_event_barnacles_ending_button" rel_version="Event_Summer_Temp">Aah!</string>
	<string key="ui_event_barnacles_calendar_event_button_about" rel_version="Event_Summer_Temp">&lt;img src="lyshineui/images/icons/misc/icon_question_orange" xPadding="0" scale="1.5" yOffset="1"&gt;&lt;/img&gt; Sobre Cracas e Pólvora Preta</string>
	<string key="ui_event_weapon_xp_title">BÔNUS DE EXP EM ARMAS ESSA SEMANA</string>
	<string key="ui_event_weapon_xp_desc">&lt;font color="#ffffff" face="lyshineui/fonts/Nimbus_Regular.font"&gt;O bônus estará disponível para:&lt;/font&gt;</string>
	<string key="ui_event_gathering_xp_title">BÔNUS DE EXP EM COLETA ESSA SEMANA</string>
	<string key="ui_event_gathering_xp_desc">&lt;font color="#ffffff" face="lyshineui/fonts/Nimbus_Regular.font"&gt;O bônus estará disponível para:&lt;/font&gt;</string>
	<string key="ui_event_character_xp_title">BÔNUS DE EXP EM NÍVEIS DE PERSONAGEM ESSA SEMANA</string>
	<string key="ui_event_character_xp_desc">&lt;font color="#ffffff" face="lyshineui/fonts/Nimbus_Regular.font"&gt;O bônus estará disponível para:&lt;/font&gt;</string>
	<string key="ui_event_refining_xp_title">BÔNUS DE EXP EM REFINAMENTO ESSA SEMANA</string>
	<string key="ui_event_refining_xp_desc">&lt;font color="#ffffff" face="lyshineui/fonts/Nimbus_Regular.font"&gt;O bônus estará disponível para:&lt;/font&gt;</string>
	<string key="ui_event_extravaganza_title">BÔNUS DE EXP À VONTADE</string>
	<string key="ui_event_extravaganza_desc">&lt;font color="#ffffff" face="lyshineui/fonts/Nimbus_Regular.font"&gt;O bônus estará disponível para:&lt;/font&gt;</string>
</resources>

