<resources xmlns:xsi="http://www.w3.org/2001/XMLSchema-instance">
	<string key="99A_MSQ_01B_04_TaskTrigger_MeetGrace" speaker="UI" rel_version="Quest_MSQ2_Revamp">Znajdź Yonasa przy drodze</string>
	<string key="99A_MSQ_02_02a_TownGuard_Prompt" speaker="UI - Player Prompt" rel_version="Quest_MSQ2_Revamp">"Właściwie to kogoś szukam".</string>
	<string key="99A_MSQ_02_02a_TownGuard_Response" speaker="Hannos Lembe" name="HannosLembe" gender="Male" VO="99A_MSQ_02_02a_TownGuard_Response" VO_Status="Script Generated" rel_version="Quest_MSQ2_Revamp">Jak my wszyscy, nieprawdaż? Jednak w tym miejscu informacje to potęga. To, co wiesz, ci, których znasz… Jeśli wiesz za dużo, możesz zatruć się trzema funtami stali. \n\nJeśli bardzo ci zależy, skontaktuj się z Sairą. Ona wie to i owo, niezależnie od tego, czy się do tego przyznaje.</string>
	<string key="99A_MSQ_10_02A_GetSilver" speaker="UI" rel_version="Quest_MSQ2_Revamp">Wydobądź kawałki srebra z gruzów</string>
	<string key="99A_MSQ_10_02B_02_SuccessEvent" speaker="UI" rel_version="Quest_MSQ2_Revamp">Dostań się do wewnętrznego azylu</string>
	<string key="99A_MSQ_10_03_DefeatEzraGetHammer" speaker="UI" rel_version="Quest_MSQ2_Revamp">Pokonaj mistrza kuźni Ezrę i zdobądź jego młot</string>
	<string key="99A_MSQ_10_04A_CraftCrosspiece" speaker="UI" rel_version="Quest_MSQ2_Revamp">Użyj pradawnej kuźni, by wytworzyć element poprzeczny</string>
</resources>

